glorpen_docker_exporter/__init__.py
glorpen_docker_exporter/__main__.py
glorpen_docker_exporter/exporter.py
glorpen_docker_exporter/metrics/__init__.py
glorpen_docker_exporter/metrics/blkio.py
glorpen_docker_exporter/metrics/container.py
glorpen_docker_exporter/metrics/memory.py
glorpen_docker_exporter/metrics/network.py
glorpen_docker_exporter/metrics/stats.py
glorpen_docker_exporter-1.0.0.dist-info/LICENSE.txt
glorpen_docker_exporter-1.0.0.dist-info/METADATA
glorpen_docker_exporter-1.0.0.dist-info/WHEEL
glorpen_docker_exporter-1.0.0.dist-info/top_level.txt
glorpen_docker_exporter-1.0.0.dist-info/RECORD
