Metadata-Version: 2.1
Name: glorpen-docker-exporter
Version: 1.0.0
Summary: Exports docker container stats as Prometheus compatible endpoint.
Home-page: https://github.com/glorpen/prometheus-docker-exporter
Author: Arkadiusz Dzięgiel
Author-email: arkadiusz.dziegiel@glorpen.pl
Project-URL: Bug Tracker, https://github.com/glorpen/prometheus-docker-exporter/issues
Classifier: Development Status :: 5 - Production/Stable
Classifier: License :: OSI Approved :: GNU General Public License v3 or later (GPLv3+)
Classifier: Intended Audience :: System Administrators
Classifier: Operating System :: POSIX :: Linux
Classifier: Programming Language :: Python :: 3.10
Classifier: Topic :: System :: Monitoring
Requires-Python: >=3.10
License-File: LICENSE.txt
Requires-Dist: docker (>=5.0.3)
Requires-Dist: prometheus-client (>=0.14.1)
